.DS_Store
pyafai/.DS_Store
pyafai/__init__.py
pyafai/__version__.py
pyafai/core.py
pyafai/influence.py
pyafai/objects.py
pyafai/shapes.py
pyafai-1.0.0rc2.dist-info/DESCRIPTION.rst
pyafai-1.0.0rc2.dist-info/METADATA
pyafai-1.0.0rc2.dist-info/RECORD
pyafai-1.0.0rc2.dist-info/WHEEL
pyafai-1.0.0rc2.dist-info/metadata.json
pyafai-1.0.0rc2.dist-info/top_level.txt
