Metadata-Version: 1.1
Name: pyafai
Version: 1.0.0rc2
Summary: Python Agent Framework for Artificial Intelligence
Home-page: https://github.com/tbaptista/pyafai
Author: Tiago Baptista
Author-email: baptista@dei.uc.pt
License: Apache License 2.0
Platform: UNKNOWN
Classifier: Development Status :: 4 - Beta
Classifier: Intended Audience :: Education
Classifier: Intended Audience :: Science/Research
Classifier: License :: OSI Approved :: Apache Software License
Classifier: Natural Language :: English
Classifier: Operating System :: OS Independent
Classifier: Programming Language :: Python :: 3
Classifier: Programming Language :: Python :: 2.7
Classifier: Topic :: Education
Classifier: Topic :: Scientific/Engineering
Classifier: Topic :: Scientific/Engineering :: Artificial Intelligence
Classifier: Topic :: Scientific/Engineering :: Artificial Life
Classifier: Topic :: Software Development :: Libraries :: Python Modules
